ipretty/__init__.py
ipretty/prettify.py
ipretty-0.0.2.dist-info/LICENSE
ipretty-0.0.2.dist-info/METADATA
ipretty-0.0.2.dist-info/WHEEL
ipretty-0.0.2.dist-info/top_level.txt
ipretty-0.0.2.dist-info/RECORD
