Metadata-Version: 2.1
Name: ipretty
Version: 0.0.2
Summary: prettify terminal output
Home-page: https://github.com/coghost/ipretty
Author: lihe
Author-email: imanux@sina.com
License: GPL
Project-URL: Bug Reports, https://github.com/coghost/ipretty/issues
Project-URL: Source, https://github.com/coghost/ipretty
Keywords: ipretty,izen,terminal,prettify,colorful
Platform: UNKNOWN
Classifier: Programming Language :: Python :: 3.7
Requires-Python: >=3.7
Requires-Dist: logzero
